hawaiio/__init__.py
hawaiio/_base.py
hawaiio/_core.py
hawaiio/py.typed
hawaiio/testing.py
hawaiio-0.0.3.dist-info/LICENSE
hawaiio-0.0.3.dist-info/METADATA
hawaiio-0.0.3.dist-info/WHEEL
hawaiio-0.0.3.dist-info/top_level.txt
hawaiio-0.0.3.dist-info/RECORD
