Metadata-Version: 2.1
Name: hawaiio
Version: 0.0.3
Summary: A library of shiny concurrency building blocks for Python
Home-page: https://github.com/florimondmanca/hawaiio.git
Author: Florimond Manca
Author-email: florimond.manca@gmail.com
License: MIT
Platform: UNKNOWN
Classifier: License :: OSI Approved :: MIT License
Classifier: Programming Language :: Python
Classifier: Programming Language :: Python :: 3
Classifier: Programming Language :: Python :: 3 :: Only
Classifier: Programming Language :: Python :: 3.6
Classifier: Programming Language :: Python :: 3.7
Classifier: Operating System :: OS Independent
Requires-Python: >=3.6
Provides-Extra: ci
Requires-Dist: pytest ; extra == 'ci'
Requires-Dist: pytest-cov ; extra == 'ci'
Requires-Dist: codecov ; extra == 'ci'
Requires-Dist: mypy ; extra == 'ci'
Provides-Extra: dev
Requires-Dist: pytest ; extra == 'dev'
Requires-Dist: pytest-cov ; extra == 'dev'
Requires-Dist: codecov ; extra == 'dev'
Requires-Dist: mypy ; extra == 'dev'
Requires-Dist: black ; extra == 'dev'
Requires-Dist: pylint ; extra == 'dev'
Requires-Dist: rope ; extra == 'dev'
Requires-Dist: bumpversion ; extra == 'dev'
